Metadata-Version: 2.1
Name: minidb
Version: 2.0.8
Summary: A simple SQLite3-based store for Python objects
Home-page: http://thp.io/2010/minidb/
Download-URL: http://thp.io/2010/minidb/minidb-2.0.8.tar.gz
Author: Thomas Perl
Author-email: m@thp.io
License: ISC
License-File: LICENSE
